tsgen/__init__.py
tsgen/generators.py
tsgen/time_serie.py
tsgen-0.6.0.dist-info/LICENSE
tsgen-0.6.0.dist-info/WHEEL
tsgen-0.6.0.dist-info/METADATA
tsgen-0.6.0.dist-info/RECORD
