Metadata-Version: 2.1
Name: tsgen
Version: 0.6.0
Summary: Time Series Generator
Home-page: https://github.com/MarwanDebbiche/tsgen
License: MIT
Keywords: time-series,data-science,time-series-analysis
Author: Marwan Debbiche
Author-email: marwan.debbiche@gmail.com
Requires-Python: >=3.6.1,<4.0.0
Classifier: License :: OSI Approved :: MIT License
Classifier: Operating System :: OS Independent
Classifier: Programming Language :: Python :: 3
Classifier: Programming Language :: Python :: 3.7
Classifier: Programming Language :: Python :: 3.8
Requires-Dist: coverage (>=5.3,<6.0)
Requires-Dist: matplotlib (>=3.3.2,<4.0.0)
Requires-Dist: numpy (>=1.19.2,<2.0.0)
Requires-Dist: pandas (>=1.1.3,<2.0.0)
Project-URL: Repository, https://github.com/MarwanDebbiche/tsgen
